kcweb/Events.py
kcweb/__init__.py
kcweb/app.py
kcweb/common/__init__.py
kcweb/common/autoload.py
kcweb/common/globals.py
kcweb/common/request.py
kcweb/common/session.py
kcweb/config/__init__.py
kcweb/tpl/err.html
kcweb/tpl/error.html
kcweb/utill/app.py
kcweb/utill/http.py
kcweb/utill/queues.py
kcweb/utill/redis.py
kcweb/utill/cache/cache.py
kcweb/utill/dateutil/__init__.py
kcweb/utill/dateutil/_common.py
kcweb/utill/dateutil/_version.py
kcweb/utill/dateutil/easter.py
kcweb/utill/dateutil/relativedelta.py
kcweb/utill/dateutil/rrule.py
kcweb/utill/dateutil/tzwin.py
kcweb/utill/dateutil/utils.py
kcweb/utill/dateutil/parser/__init__.py
kcweb/utill/dateutil/parser/_parser.py
kcweb/utill/dateutil/parser/isoparser.py
kcweb/utill/dateutil/tz/__init__.py
kcweb/utill/dateutil/tz/_common.py
kcweb/utill/dateutil/tz/_factories.py
kcweb/utill/dateutil/tz/tz.py
kcweb/utill/dateutil/tz/win.py
kcweb/utill/dateutil/zoneinfo/__init__.py
kcweb/utill/dateutil/zoneinfo/rebuild.py
kcweb/utill/db/model.py
kcweb/utill/db/mongodb.py
kcweb/utill/db/mysql.py
kcweb/utill/db/sqlite copy.py
kcweb/utill/db/sqlite.py
kcweb/utill/db/pymysql/__init__.py
kcweb/utill/db/pymysql/_auth.py
kcweb/utill/db/pymysql/_compat.py
kcweb/utill/db/pymysql/_socketio.py
kcweb/utill/db/pymysql/charset.py
kcweb/utill/db/pymysql/connections.py
kcweb/utill/db/pymysql/converters.py
kcweb/utill/db/pymysql/cursors.py
kcweb/utill/db/pymysql/err.py
kcweb/utill/db/pymysql/optionfile.py
kcweb/utill/db/pymysql/protocol.py
kcweb/utill/db/pymysql/times.py
kcweb/utill/db/pymysql/util.py
kcweb/utill/db/pymysql/constants/CLIENT.py
kcweb/utill/db/pymysql/constants/COMMAND.py
kcweb/utill/db/pymysql/constants/CR.py
kcweb/utill/db/pymysql/constants/ER.py
kcweb/utill/db/pymysql/constants/FIELD_TYPE.py
kcweb/utill/db/pymysql/constants/FLAG.py
kcweb/utill/db/pymysql/constants/SERVER_STATUS.py
kcweb/utill/db/pymysql/constants/__init__.py
kcweb/utill/db/sqlitedata/kcwdb
kcweb/utill/filetype/__init__.py
kcweb/utill/filetype/filetype.py
kcweb-4.13.31.dist-info/METADATA
kcweb-4.13.31.dist-info/WHEEL
kcweb-4.13.31.dist-info/entry_points.txt
kcweb-4.13.31.dist-info/license_files/LICENSE
kcweb-4.13.31.dist-info/RECORD
