Metadata-Version: 2.1
Name: kcweb
Version: 4.13.31
Summary: socket服务修复
Project-URL: Bug Tracker, https://gitee.com/open_source_official_website/kcweb/
Project-URL: Homepage, https://gitee.com/open_source_official_website/kcweb/
Author-email: 百里 <fk1402936534@qq.com>
Classifier: License :: OSI Approved :: MIT License
Classifier: Programming Language :: Python :: 3
Requires-Python: >=3.6
Requires-Dist: mako>=1.1.2
Requires-Dist: pymongo>=3.10.0
Requires-Dist: requests>=2.23.0
Requires-Dist: six>=1.12.0
Requires-Dist: watchdog>=0.9.0
Requires-Dist: websockets==8.1
